{"cameraMode":{"drawMode":0,"name":"Shaded","section":"Shading Mode"},"sceneLighting":false,"audioPlay":false,"sceneViewState":{"m_AlwaysRefresh":false,"showFog":true,"showSkybox":false,"showFlares":true,"showImageEffects":true,"showParticleSystems":true,"showVisualEffectGraphs":true,"m_FxEnabled":true},"in2DMode":false,"pivot":{"x":45.33692169189453,"y":3.922717332839966,"z":16.501035690307618},"rotation":{"x":0.1330554038286209,"y":0.7522704005241394,"z":-0.15787871181964875,"w":0.6261223554611206},"size":1.8520350456237794,"orthographic":false}